remoterunlib/__init__.py
remoterunlib/dashboard.py
remoterunlib/remoterunlib.py
remoterunlib/UI/index.html
remoterunlib/UI/script.js
remoterunlib/UI/styles.css
remoterunlib/utils.py
remoterunlib-0.8.1.dist-info/entry_points.txt
remoterunlib-0.8.1.dist-info/LICENSE
remoterunlib-0.8.1.dist-info/METADATA
remoterunlib-0.8.1.dist-info/WHEEL
remoterunlib-0.8.1.dist-info/RECORD
