Metadata-Version: 2.3
Name: remoterunlib
Version: 0.8.1
Summary: Enterprise remote management library for SSH, Docker, Ansible, Terraform, PowerShell, and web dashboard automation.
License: MIT
Author: Sharath Kumar
Author-email: dsharathrao@gmail.com
Requires-Python: >=3.6
Classifier: Development Status :: 3 - Alpha
Classifier: Environment :: Console
Classifier: Intended Audience :: Developers
Classifier: License :: OSI Approved :: MIT License
Classifier: Operating System :: OS Independent
Classifier: Programming Language :: Python
Classifier: Programming Language :: Python :: 3
Classifier: Programming Language :: Python :: 3.6
Classifier: Programming Language :: Python :: 3.7
Classifier: Programming Language :: Python :: 3.8
Classifier: Programming Language :: Python :: 3.9
Classifier: Programming Language :: Python :: 3.10
Classifier: Programming Language :: Python :: 3.11
Classifier: Programming Language :: Python :: 3.12
Classifier: Programming Language :: Python :: 3.13
Requires-Dist: ansible (>=8.7.0,<9.0.0) ; sys_platform == "linux"
Requires-Dist: flask-cors (>=4.0.0,<5.0.0)
Requires-Dist: flask-socketio (>=5.5.0,<6.0.0)
Requires-Dist: paramiko (==3.4.0)
Project-URL: Bug Tracker, https://github.com/dsharathrao/remoterunlib/issues
Project-URL: Repository, https://github.com/dsharathrao/remoterunlib
